{"type":"","identifier":"fst00031384","alt-identifier":["fst00031384"],"old-identifier":[""],"other-identifier":["(DLC)n  79018757 ","(uri)http://en.wikipedia.org/wiki/Richard_Nixon","(viaf)44303100"],"heading":["Nixon, Richard M.. (Richard Milhous),. 1913-1994. "],"alt-heading":["Ni-k\ufffdo-sung,. 1913-1994. ","Nikesong,. 1913-1994. ","Nikson, Ri\ufffdcard Milhaus,. 1913-1994. ","Ni-k\ufffdo-hs\ufffdun,. 1913-1994. ","Nikexun,. 1913-1994. ","Nikesen,. 1913-1994. ","Ni-k\ufffdo-sen,. 1913-1994. ","Niks\ufffdun, R\ufffditsh\ufffdard,. 1913-1994. ","Nixon, Richard Milhous,. 1913-1994. ","Nixon, Richard,. 1913-1994. ","Nixon, Richard M.. (Richard Milhous),. 1913-1994. ","Richard Nixon. Feb2015. ","Nixon, Richard M.. (Richard Milhous),. 1913-1994. Feb2015. "],"west-coordinate":null,"east-coordinate":null,"north-coordinate":null,"south-coordinate":null,"marc-geo-code":null,"classification":null,"start-date":[""],"death-date":["19940422"],"end-date":[""],"meeting-type":null,"meeting-info":null,"country":[""],"headquarters":["Washington, D.C."],"location":[""],"place-of-origin":[""],"field-of-action":["Government"],"group":null,"language":["eng"],"general-note":null}