{"type":"","identifier":"fst00057780","alt-identifier":["fst00057780"],"old-identifier":[""],"other-identifier":["(DLC)n 80089962","(viaf)3776109"],"heading":["Raalte, E. van. (Ernst),. 1892-1975. "],"alt-heading":["Raalte, Ernst van,. 1892-1975. ","Van Raalte, E.. (Ernst),. 1892-1975. ","Raalte, E. van. (Ernst),. 1892-1975. ","Raalte, Ernst van,. 1892-1975. Feb2015. "],"west-coordinate":null,"east-coordinate":null,"north-coordinate":null,"south-coordinate":null,"marc-geo-code":null,"classification":null,"start-date":[""],"death-date":["1975"],"end-date":[""],"meeting-type":null,"meeting-info":null,"country":null,"headquarters":null,"location":null,"place-of-origin":null,"field-of-action":["Netherlands--Politics and government"],"group":null,"language":["dut"],"general-note":null}