{"type":"","identifier":"fst00056457","alt-identifier":["fst00056457"],"old-identifier":[""],"other-identifier":["(DLC)n  80075853 ","(uri)http://en.wikipedia.org/wiki/Frances_Burney","(viaf)95297439"],"heading":["Burney, Fanny,. 1752-1840. "],"alt-heading":["Arblay, Frances Burney d',. 1752-1840. ","Arblay,. Madame d',. 1752-1840. ","Author of Camilla,. 1752-1840. ","Author of Evelina,. 1752-1840. ","Author of Evelina and Cecilia,. 1752-1840. ","B\ufffdi\ufffdurne\ufffdi,. gospozha,. 1752-1840. ","Burne\ufffdi,. Miss,. 1752-1840. ","Burney, Frances,. 1752-1840. ","Burney, Frances Anne,. 1752-1840. ","Camilla, Author of,. 1752-1840. ","D'Arblay, Fanny,. 1752-1840. ","D'Arblay, Frances Burney,. 1752-1840. ","D'Arblay,. Madame,. 1752-1840. ","Evelina and Cecilia, Author of,. 1752-1840. ","Evelina, Author of,. 1752-1840. ","Wood,. Mrs.. (Fanny),. 1752-1840. ","Burney, Fanny,. 1752-1840. ","Frances Burney. Feb2015. ","Burney, Fanny,. 1752-1840. Feb2015. "],"west-coordinate":null,"east-coordinate":null,"north-coordinate":null,"south-coordinate":null,"marc-geo-code":null,"classification":["PR3316.A4. "],"start-date":null,"death-date":null,"end-date":null,"meeting-type":null,"meeting-info":null,"country":[""],"headquarters":[""],"location":[""],"place-of-origin":[""],"field-of-action":null,"group":null,"language":["eng"],"general-note":null}