{"type":"","identifier":"fst00047765","alt-identifier":["fst00047765"],"old-identifier":[""],"other-identifier":["(DLC)n  79148555 ","(viaf)28361354"],"heading":["R\ufffdognvaldur Sigurj\ufffdonsson,. 1918-. "],"alt-heading":["Sigurj\ufffdonsson, R\ufffdognvaldur,. 1918-. ","Sigurj\ufffdonsson, R.. (R\ufffdognvaldur),. 1918-. ","R\ufffdognvaldur Sigurj\ufffdonsson,. 1918-. ","R\ufffdognvaldur Sigurj\ufffdonsson,. 1918-. Feb2015. "],"west-coordinate":null,"east-coordinate":null,"north-coordinate":null,"south-coordinate":null,"marc-geo-code":null,"classification":null,"start-date":null,"death-date":null,"end-date":null,"meeting-type":null,"meeting-info":null,"country":null,"headquarters":null,"location":null,"place-of-origin":null,"field-of-action":null,"group":null,"language":null,"general-note":null}