{"type":"","identifier":"fst00068343","alt-identifier":["fst00068343"],"old-identifier":[""],"other-identifier":["(DLC)n  81020170 ","(viaf)61524587"],"heading":["Larreta, Antonio,. 1922-. "],"alt-heading":["Larreta, Antonio,. 1922-. ","Larreta, Antonio,. 1922-. Feb2015. "],"west-coordinate":null,"east-coordinate":null,"north-coordinate":null,"south-coordinate":null,"marc-geo-code":null,"classification":["PQ8520.22.A7. "],"start-date":null,"death-date":null,"end-date":null,"meeting-type":null,"meeting-info":null,"country":null,"headquarters":null,"location":null,"place-of-origin":null,"field-of-action":null,"group":null,"language":null,"general-note":null}