{"type":"","identifier":"fst00031338","alt-identifier":["fst00031338"],"old-identifier":[""],"other-identifier":["(DLC)n  79018563 ","(viaf)75120861"],"heading":["Cleland, Thomas,. 1778-1858. "],"alt-heading":["Clelland, Thomas,. 1778-1858. ","Cleland, Thomas,. 1778-1858. ","Cleland, Thomas,. 1778-1858. Feb2015. "],"west-coordinate":null,"east-coordinate":null,"north-coordinate":null,"south-coordinate":null,"marc-geo-code":null,"classification":null,"start-date":null,"death-date":null,"end-date":null,"meeting-type":null,"meeting-info":null,"country":null,"headquarters":null,"location":null,"place-of-origin":null,"field-of-action":null,"group":null,"language":null,"general-note":null}