{"type":"","identifier":"fst00062176","alt-identifier":["fst00062176"],"old-identifier":[""],"other-identifier":["(DLC)n  80132205 ","(uri)http://en.wikipedia.org/wiki/James_Curtis_Hepburn","(viaf)6242432"],"heading":["Hepburn, J. C.. (James Curtis),. 1815-1911. "],"alt-heading":["Hebon,. 1815-1911. ","Hepburn, James Curtis,. 1815-1911. ","Hepburn, J. C.. (James Curtis),. 1815-1911. ","James Curtis Hepburn. Feb2015. ","Hepburn, J. C.. (James Curtis),. 1815-1911. Feb2015. "],"west-coordinate":null,"east-coordinate":null,"north-coordinate":null,"south-coordinate":null,"marc-geo-code":null,"classification":null,"start-date":null,"death-date":null,"end-date":null,"meeting-type":null,"meeting-info":null,"country":null,"headquarters":null,"location":null,"place-of-origin":null,"field-of-action":null,"group":null,"language":null,"general-note":null}