{"type":"","identifier":"fst00006354","alt-identifier":["fst00006354"],"old-identifier":[""],"other-identifier":["(DLC)n  50019664 ","(uri)http://en.wikipedia.org/wiki/L._P._Vidyarthi","(viaf)56624646"],"heading":["Vidyarthi, Lalita Prasad. "],"alt-heading":["Vidyarthi, L. P.. (Lalita Prasad). ","Vidyarthy, Lalita Prasad. ","Vidhy\ufffdarth\ufffdi, Lalit\ufffda Pras\ufffdada. ","Lalit\ufffda Pras\ufffdada Vidhy\ufffdarth\ufffdi. ","Vidyarthi, Lalita Prasad. ","L. P. Vidyarthi. Feb2015. ","Vidyarthi, Lalita Prasad. Feb2015. "],"west-coordinate":null,"east-coordinate":null,"north-coordinate":null,"south-coordinate":null,"marc-geo-code":null,"classification":null,"start-date":[""],"death-date":[""],"end-date":[""],"meeting-type":null,"meeting-info":null,"country":null,"headquarters":null,"location":null,"place-of-origin":null,"field-of-action":null,"group":null,"language":null,"general-note":null}