{"type":"","identifier":"fst00049968","alt-identifier":["fst00049968"],"old-identifier":[""],"other-identifier":["(DLC)n  80015568 ","(uri)http://en.wikipedia.org/wiki/Aristide_Maillol","(viaf)14228"],"heading":["Maillol, Aristide,. 1861-1944. "],"alt-heading":["Maillol, Aristide Joseph Bonaventure,. 1861-1944. ","Maiyue, Alisidide,. 1861-1944. ","Maillol, Aristide,. 1861-1944. ","Aristide Maillol. Feb2015. ","Maillol, Aristide,. 1861-1944. Feb2015. "],"west-coordinate":null,"east-coordinate":null,"north-coordinate":null,"south-coordinate":null,"marc-geo-code":null,"classification":null,"start-date":[""],"death-date":["19440927"],"end-date":[""],"meeting-type":null,"meeting-info":null,"country":[""],"headquarters":[""],"location":["Pyr\ufffden\ufffdees-Orientales, France"],"place-of-origin":[""],"field-of-action":null,"group":["Mus\ufffdee Maillol"],"language":null,"general-note":null}