{"type":"","identifier":"fst00034395","alt-identifier":["fst00034395"],"old-identifier":[""],"other-identifier":["(DLC)n  79045138 ","(uri)http://en.wikipedia.org/wiki/Jan_Mikusin%CC%81ski","(viaf)68976059"],"heading":["Mikusi\ufffdnski, Jan. "],"alt-heading":["Mikusinski\ufffdi, \ufffdI\ufffdA. ","Mikusi\ufffdnski, Jan. ","Jan Mikusi\ufffdnski. Feb2015. ","Mikusi\ufffdnski, Jan. Feb2015. "],"west-coordinate":null,"east-coordinate":null,"north-coordinate":null,"south-coordinate":null,"marc-geo-code":null,"classification":null,"start-date":null,"death-date":null,"end-date":null,"meeting-type":null,"meeting-info":null,"country":null,"headquarters":null,"location":null,"place-of-origin":null,"field-of-action":null,"group":null,"language":null,"general-note":null}