{"type":"","identifier":"fst00004021","alt-identifier":["fst00004021"],"old-identifier":[""],"other-identifier":["(DLC)n  50013163 ","(uri)http://en.wikipedia.org/wiki/Clement_Wood","(viaf)24967953"],"heading":["Wood, Clement,. 1888-1950. "],"alt-heading":["Wood, Clement,. 1888-1950. ","Clement Wood. Feb2015. ","Wood, Clement,. 1888-1950. Feb2015. "],"west-coordinate":null,"east-coordinate":null,"north-coordinate":null,"south-coordinate":null,"marc-geo-code":null,"classification":["PS3545.O4715. "],"start-date":[""],"death-date":["19501026"],"end-date":[""],"meeting-type":null,"meeting-info":null,"country":[""],"headquarters":["Birmingham, Ala."],"location":[""],"place-of-origin":[""],"field-of-action":["Law"],"group":["Barnard School for Boys","New York University"],"language":["eng"],"general-note":null}