{"type":"","identifier":"fst00029969","alt-identifier":["fst00029969"],"old-identifier":[""],"other-identifier":["(DLC)n 79005084","(viaf)79258394"],"heading":["Evans, Margaret,. 1930-. "],"alt-heading":["Evans, Doreen Margaret,. 1930-. ","Evans, Margaret,. active 1978. ","Evans, Margaret. ","Evans, Margaret,. 1930-. ","Evans, Margaret. Feb2015. "],"west-coordinate":null,"east-coordinate":null,"north-coordinate":null,"south-coordinate":null,"marc-geo-code":null,"classification":null,"start-date":null,"death-date":null,"end-date":null,"meeting-type":null,"meeting-info":null,"country":["Great Britain"],"headquarters":[""],"location":[""],"place-of-origin":[""],"field-of-action":["Fiction"],"group":null,"language":["eng"],"general-note":null}