{"type":"","identifier":"fst00060745","alt-identifier":["fst00060745"],"old-identifier":[""],"other-identifier":["(DLC)n  80118646 ","(viaf)23447702"],"heading":["C\ufffdetur\ufffdama\ufffdn, Tirumu\ufffdti Na.,. 1923-1979. "],"alt-heading":["C\ufffdetur\ufffdama\ufffdn, Na.,. 1923-1979. ","Sethuraman, N.,. 1923-1979. ","Tirumu\ufffdtiy\ufffdar,. 1923-1979. ","Tirumu\ufffdti C\ufffdetur\ufffdama\ufffdn,. 1923-1979. ","C\ufffdetur\ufffdama\ufffdn, Tirumu\ufffdti,. 1923-1979. ","C\ufffdetur\ufffdama\ufffdn, Tirumu\ufffdti Na.,. 1923-1979. ","C\ufffdetur\ufffdama\ufffdn, Tirumu\ufffdti Na.,. 1923-1979. Feb2015. "],"west-coordinate":null,"east-coordinate":null,"north-coordinate":null,"south-coordinate":null,"marc-geo-code":null,"classification":null,"start-date":null,"death-date":null,"end-date":null,"meeting-type":null,"meeting-info":null,"country":null,"headquarters":null,"location":null,"place-of-origin":null,"field-of-action":null,"group":null,"language":null,"general-note":null}