{"type":"","identifier":"fst00050248","alt-identifier":["fst00050248"],"old-identifier":["fst01571886"],"other-identifier":["(DLC)n 80017688","(viaf)5104415","(uri)http://en.wikipedia.org/wiki/Desi_Sangye_Gyatso"],"heading":["Sangs-rgyas-rgya-mtsho,. Sde-srid,. 1653-1705. "],"alt-heading":["Chzham\ufffdt\ufffdso, D\ufffdesrid Sanchzha\ufffdi-,. 1653-1705. ","Disi Sangjiejiacuo,. 1653-1705. ","Gyamtso, Sangye,. 1653-1705. ","Gyatso, Sangye,. Sde-srid,. 1653-1705. ","Sanchzha\ufffdi-Chzham\ufffdt\ufffdso, D\ufffdesrid,. 1653-1705. ","Sang-chieh-chia-t\ufffdso,. Ti-ssu,. 1653-1705. ","Sangjayijamsu,. Ovseride,. 1653-1705. ","Sangjiejiacuo,. Disi,. 1653-1705. ","Sangs-rgyas rGya-mtsho,. 1653-1705. ","Sangy\ufffde Gyatso,. Desi,. 1653-1705. ","Sangye Gyatso,. Sde-srid,. 1653-1705. ","Sa\ufffdns-rgya-rgya-mtsho,. Sde-srid,. 1653-1705. ","Sa\ufffdns-rgyas-rgya-mtsho,. Sde-srid,. 1653-1705. ","Sde-srid Sangs-rgyas-rgya-mtsho,. 1653-1705. ","Ti-ssu Sang-chieh-chia-t\ufffdso,. 1653-1705. ","Sangs-rgyas-rgya-mtsho,. Sde-srid,. 1653-1705. ","Sa\ufffdns-rgyas-rgya-mtsho,. Sde-srid,. 1653-1705. Feb2015. ","Desi Sangye Gyatso. Feb2015. "],"west-coordinate":null,"east-coordinate":null,"north-coordinate":null,"south-coordinate":null,"marc-geo-code":null,"classification":null,"start-date":[""],"death-date":["1705"],"end-date":[""],"meeting-type":null,"meeting-info":null,"country":null,"headquarters":null,"location":null,"place-of-origin":null,"field-of-action":null,"group":null,"language":null,"general-note":null}