{"type":"","identifier":"fst00014865","alt-identifier":["fst00014865"],"old-identifier":[""],"other-identifier":["(DLC)n  50043159 ","(uri)http://en.wikipedia.org/wiki/Rene%CC%81_Boylesve","(viaf)22159286"],"heading":["Boylesve, Ren\ufffde,. 1867-1926. "],"alt-heading":["Tardivaux, Ren\ufffde,. 1867-1926. ","Boylesve, Ren\ufffde,. 1867-1926. ","Ren\ufffde Boylesve. Feb2015. ","Boylesve, Ren\ufffde,. 1867-1926. Feb2015. "],"west-coordinate":null,"east-coordinate":null,"north-coordinate":null,"south-coordinate":null,"marc-geo-code":null,"classification":["PQ2603.O9. "],"start-date":null,"death-date":null,"end-date":null,"meeting-type":null,"meeting-info":null,"country":null,"headquarters":null,"location":null,"place-of-origin":null,"field-of-action":null,"group":null,"language":null,"general-note":null}