{"type":"","identifier":"fst00033445","alt-identifier":["fst00033445"],"old-identifier":[""],"other-identifier":["(DLC)n  79038460 ","(uri)http://en.wikipedia.org/wiki/Giuseppe_Verdi","(viaf)22329110"],"heading":["Verdi, Giuseppe,. 1813-1901. "],"alt-heading":["Verdi, D.,. 1813-1901. ","Verdi, Dzh.,. 1813-1901. ","Verdi, Dzhuzepe,. 1813-1901. ","Verdi, Fortunino Giuseppe Francesco,. 1813-1901. ","Verdi, G.. (Giuseppe),. 1813-1901. ","Verdi, Giuseppo,. 1813-1901. ","Verdi, Jakab,. 1813-1901. ","Verdi, Joseph,. 1813-1901. ","Verdi, J\ufffdozsef,. 1813-1901. ","Verdis, D\ufffdz.,. 1813-1901. ","Verudi, G.,. 1813-1901. ","Wei'erdi,. 1813-1901. ","Verdi, Giuseppe,. 1813-1901. ","Giuseppe Verdi. Feb2015. ","Verdi, Giuseppe,. 1813-1901. Feb2015. "],"west-coordinate":null,"east-coordinate":null,"north-coordinate":null,"south-coordinate":null,"marc-geo-code":null,"classification":["ML410.V4. Biography. "],"start-date":["",""],"death-date":["","19010127"],"end-date":["",""],"meeting-type":null,"meeting-info":null,"country":[""],"headquarters":[""],"location":[""],"place-of-origin":[""],"field-of-action":null,"group":null,"language":["ita"],"general-note":null}