{"type":"","identifier":"fst00040290","alt-identifier":["fst00040290"],"old-identifier":[""],"other-identifier":["(DLC)n  79086339 ","(uri)http://en.wikipedia.org/wiki/Margaret_Anna_Cusack","(viaf)61923351"],"heading":["Cusack, Mary Francis,. 1829-1899. "],"alt-heading":["Cusack, M. F.. (Mary Francis),. 1829-1899. ","Cusack, Margaret Anna,. 1829-1899. ","Mary Francis Clare,. Sister,. 1829-1899. ","Religious of the Order of Poor Clares,. 1829-1899. ","Cusack, C. F.,. 1829-1899. ","Cusack, Mary Francis,. 1829-1899. ","Margaret Anna Cusack. Feb2015. ","Cusack, Mary Francis,. 1829-1899. Feb2015. "],"west-coordinate":null,"east-coordinate":null,"north-coordinate":null,"south-coordinate":null,"marc-geo-code":null,"classification":null,"start-date":[""],"death-date":["1899"],"end-date":[""],"meeting-type":null,"meeting-info":null,"country":null,"headquarters":null,"location":null,"place-of-origin":null,"field-of-action":null,"group":null,"language":null,"general-note":null}