{"type":"","identifier":"fst00028963","alt-identifier":["fst00028963"],"old-identifier":[""],"other-identifier":["(DLC)n  78094254 ","(viaf)65271419"],"heading":["Johnson, A. F.. "],"alt-heading":["Johnson, Alastair Frank. ","Johnson, A. F.. ","Johnson, A. F.. Feb2015. "],"west-coordinate":null,"east-coordinate":null,"north-coordinate":null,"south-coordinate":null,"marc-geo-code":null,"classification":null,"start-date":["19"],"death-date":[""],"end-date":[""],"meeting-type":null,"meeting-info":null,"country":null,"headquarters":null,"location":null,"place-of-origin":null,"field-of-action":["Engineering"],"group":null,"language":["eng"],"general-note":null}