{"type":"","identifier":"fst00017659","alt-identifier":["fst00017659"],"old-identifier":[""],"other-identifier":["(DLC)n  50052093 ","(uri)http://en.wikipedia.org/wiki/Konstantin_Leontiev","(viaf)19680377"],"heading":["Leont\ufffdev, Konstantin,. 1831-1891. "],"alt-heading":["Leont\ufffdev, K. N.. (Konstantin Nikolaevich),. 1831-1891. ","Leont\ufffdev, Konstantin Nikolaevich,. 1831-1891. ","Leontieff, Constantin,. 1831-1891. ","Leontieph, K. N.,. 1831-1891. ","Leontiev, Konstantin,. 1831-1891. ","Leontyev, Konstantin Nikolayevi\ufffdc,. 1831-1891. ","Leont\ufffdev, Konstantin,. 1831-1891. ","Konstantin Leontiev. Feb2015. ","Leont\ufffdev, Konstantin,. 1831-1891. Feb2015. "],"west-coordinate":null,"east-coordinate":null,"north-coordinate":null,"south-coordinate":null,"marc-geo-code":null,"classification":["PG3467.L4. "],"start-date":[""],"death-date":["18911112"],"end-date":[""],"meeting-type":null,"meeting-info":null,"country":null,"headquarters":null,"location":null,"place-of-origin":null,"field-of-action":null,"group":null,"language":["rus"],"general-note":null}