{"type":"","identifier":"fst00069741","alt-identifier":["fst00069741"],"old-identifier":[""],"other-identifier":["(OCoLC)fst01841778","(DLC)n  81030847 "],"heading":["Pokou,. Queen of the Baoul\ufffde,. 1700-ca. 1760. "],"alt-heading":["Abla Pokou,. Queen of the Baoul\ufffde,. 1700-ca. 1760. ","Poku,. Queen of the Baoul\ufffde,. 1700-ca. 1760. ","Pokou,. Queen of the Baoul\ufffde,. 1700-approximately 1760. fast. ","Pokou,. Queen of the Baoul\ufffde,. 1700-ca. 1760. "],"west-coordinate":null,"east-coordinate":null,"north-coordinate":null,"south-coordinate":null,"marc-geo-code":null,"classification":null,"start-date":null,"death-date":null,"end-date":null,"meeting-type":null,"meeting-info":null,"country":null,"headquarters":null,"location":null,"place-of-origin":null,"field-of-action":null,"group":null,"language":null,"general-note":null}