{"type":"","identifier":"fst00025553","alt-identifier":["fst00025553"],"old-identifier":[""],"other-identifier":["(DLC)n  78051734 ","(viaf)35714646"],"heading":["Paterson, Judith Hillman,. 1936-. "],"alt-heading":["Jones, Judith P.. ","Paterson, Judith,. 1938-. ","Paterson, Judith Hillman,. 1936-. ","Paterson, Judith Hillman,. 1936-. Feb2015. "],"west-coordinate":null,"east-coordinate":null,"north-coordinate":null,"south-coordinate":null,"marc-geo-code":null,"classification":null,"start-date":null,"death-date":null,"end-date":null,"meeting-type":null,"meeting-info":null,"country":null,"headquarters":null,"location":null,"place-of-origin":null,"field-of-action":null,"group":null,"language":null,"general-note":null}