{"type":"","identifier":"fst00004799","alt-identifier":["fst00004799"],"old-identifier":[""],"other-identifier":["(DLC)n  50015437 ","(uri)http://en.wikipedia.org/wiki/Arno_C._Gaebelein","(viaf)249894"],"heading":["Gaebelein, Arno Clemens,. 1861-1945. "],"alt-heading":["Gaebelein, Arno C.. (Arno Clemens),. 1861-1945. ","Gaebelein, Arno Clemens,. 1861-1945. ","Arno C. Gaebelein. Feb2015. ","Gaebelein, Arno Clemens,. 1861-1945. Feb2015. "],"west-coordinate":null,"east-coordinate":null,"north-coordinate":null,"south-coordinate":null,"marc-geo-code":null,"classification":null,"start-date":null,"death-date":null,"end-date":null,"meeting-type":null,"meeting-info":null,"country":null,"headquarters":null,"location":null,"place-of-origin":null,"field-of-action":null,"group":null,"language":null,"general-note":null}