{"type":"","identifier":"fst00009010","alt-identifier":["fst00009010"],"old-identifier":[""],"other-identifier":["(DLC)n  50027226 ","(viaf)261113238"],"heading":["Drapkin, Israel,. 1905-. "],"alt-heading":["Drapkin Shenderey, Israel,. 1905-. ","Shenderey, Israel Drapkin,. 1905-. ","Senderey, Israel Drapkin,. 1905-. ","Drap\ufffdkin, Yi\ufffdsra\ufffdel,. 1905-. ","Drapkin Senderey, Israel,. 1905-. ","Drapkin, Israel,. 1905-. ","Drapkin, Israel,. 1905-. Feb2015. "],"west-coordinate":null,"east-coordinate":null,"north-coordinate":null,"south-coordinate":null,"marc-geo-code":null,"classification":null,"start-date":[""],"death-date":[""],"end-date":[""],"meeting-type":null,"meeting-info":null,"country":null,"headquarters":null,"location":null,"place-of-origin":null,"field-of-action":null,"group":null,"language":null,"general-note":null}