{"type":"","identifier":"fst00063785","alt-identifier":["fst00063785"],"old-identifier":[""],"other-identifier":["(DLC)n 80146118","(uri)http://en.wikipedia.org/wiki/Nikolay_Diletsky","(viaf)161310037"],"heading":["Dile\ufffdt\ufffds\ufffdky\ufffdi, Mykola. "],"alt-heading":["Diletski, Nikola\ufffdi. ","Dile\ufffdt\ufffdski\ufffdi, Nikola\ufffdi. ","Dile\ufffdt\ufffdski\ufffdi, Nikola\ufffdi Pavlovich. ","Diletsky, Mikola. ","Diletsky, Nikolai. ","Dilezki, Mykola\ufffdi. ","Dyle\ufffdt\ufffds\ufffdky\ufffdi, Mykola. ","Dyle\ufffdt\ufffds\ufffdky\ufffdi, Mykola Pavlovych. ","Dile\ufffdt\ufffds\ufffdky\ufffdi, Mykola. ","Nikolay Diletsky. Feb2015. ","Dyle\ufffdt\ufffds\ufffdky\ufffdi, Mykola Pavlovych. Feb2015. "],"west-coordinate":null,"east-coordinate":null,"north-coordinate":null,"south-coordinate":null,"marc-geo-code":null,"classification":null,"start-date":null,"death-date":null,"end-date":null,"meeting-type":null,"meeting-info":null,"country":[""],"headquarters":[""],"location":[""],"place-of-origin":[""],"field-of-action":null,"group":null,"language":null,"general-note":null}