{"type":"","identifier":"fst00033898","alt-identifier":["fst00033898"],"old-identifier":[""],"other-identifier":["(DLC)n  79041967 ","(viaf)41942889","(uri)http://en.wikipedia.org/wiki/Harbhajan_Singh_Khalsa"],"heading":["Bhajan,. Yogi,. 1929-2004. "],"alt-heading":["Harabhajana Si\ufffdngha \ufffdK\ufffdh\ufffdalas\ufffda,. Yogiji,. 1929-2004. ","Harabhajana Si\ufffdngha,. Yog\ufffdi,. 1929-2004. ","Harbhajan Singh Khalsa,. Yogiji,. 1929-2004. ","Harbhajan Singh Khalsa,. Yogiji. ","Harbhajan Singh,. Yogi,. 1929-2004. ","Harbhajan,. Yogi,. 1929-2004. ","\ufffdK\ufffdh\ufffdalas\ufffda, Harabhajana Si\ufffdngha,. Yogiji,. 1929-2004. ","Khalsa, Harbhajan Singh,. Yogiji,. 1929-2004. ","Puri, Harbhajan Singh,. 1929-2004. ","Singh, Harbhajan,. Yogi,. 1929-2004. ","Singh,. Yogi,. 1929-2004. ","Si\ufffdngha,. Yog\ufffdi,. 1929-2004. ","Yogi Bhajan,. 1929-2004. ","Yogi Harbhajan,. 1929-2004. ","Bhajan,. Yogi,. 1929-2004. ","Bhajan,. Yogi,. 1929-2004. Feb2015. ","Harbhajan Singh Khalsa. Feb2015. "],"west-coordinate":null,"east-coordinate":null,"north-coordinate":null,"south-coordinate":null,"marc-geo-code":null,"classification":null,"start-date":[""],"death-date":["20041006"],"end-date":[""],"meeting-type":null,"meeting-info":null,"country":null,"headquarters":null,"location":null,"place-of-origin":null,"field-of-action":null,"group":null,"language":null,"general-note":null}