{"type":"","identifier":"fst00055027","alt-identifier":["fst00055027"],"old-identifier":[""],"other-identifier":["(OCoLC)fst01860587","(DLC)n  80060684 "],"heading":["Giuliotti, Domenico,. 1877-. "],"alt-heading":["Giuliotti, Domenico,. 1877-1956. fast. ","Giuliotti, Domenico,. 1877-. "],"west-coordinate":null,"east-coordinate":null,"north-coordinate":null,"south-coordinate":null,"marc-geo-code":null,"classification":["PQ4817.I854. "],"start-date":null,"death-date":null,"end-date":null,"meeting-type":null,"meeting-info":null,"country":null,"headquarters":null,"location":null,"place-of-origin":null,"field-of-action":null,"group":null,"language":null,"general-note":null}