{"type":"","identifier":"fst00002852","alt-identifier":["fst00002852"],"old-identifier":[""],"other-identifier":["(DLC)n  50009833 ","(uri)http://en.wikipedia.org/wiki/Bessie_Louise_Pierce","(viaf)52927625"],"heading":["Pierce, Bessie Louise,. 1888-1974. "],"alt-heading":["Pierce, Bessie Louise,. 1888-1974. ","Bessie Louise Pierce. Feb2015. ","Pierce, Bessie Louise,. 1888-1974. Feb2015. "],"west-coordinate":null,"east-coordinate":null,"north-coordinate":null,"south-coordinate":null,"marc-geo-code":null,"classification":null,"start-date":null,"death-date":null,"end-date":null,"meeting-type":null,"meeting-info":null,"country":null,"headquarters":null,"location":null,"place-of-origin":null,"field-of-action":null,"group":null,"language":null,"general-note":null}