{"type":"","identifier":"sh2013000058","alt-identifier":["sh2013000058"],"old-identifier":[""],"heading":["Zhongguo guan (Expo, International Exhibitions Bureau, 2010, Shanghai, China). "],"alt-heading":["China Pavilion (Expo, International Exhibitions Bureau, 2010, Shanghai, China). ","Dong fang zhi guan (Expo, International Exhibitions Bureau, 2010, Shanghai, China). ","Oriental Crown (Expo, International Exhibitions Bureau, 2010, Shanghai, China). ","Zhongguo guan (Shanghai World Expo, 2010, China). ","Zhongguo guo jia guan (Expo, International Exhibitions Bureau, 2010, Shanghai, China). ","Exhibition buildings. China. "],"west-coordinate":null,"east-coordinate":null,"north-coordinate":null,"south-coordinate":null,"marc-geo-code":null,"classification":null,"general-note":null}