{"type":"","identifier":"sh2011000339","alt-identifier":["sh2011000339"],"old-identifier":[""],"heading":["Altan Ovoo Mountain (Mongolia). "],"alt-heading":["Mountains. Mongolia. ","A-t'ung-ao-pao Mountain (Mongolia). ","Altan-obo Mountain (Mongolia). ","Altan Obuġ-a Mountain (Mongolia). ","Altan Ovoo (Mongolia : Mountain). ","Altan Ovoo Uul (Mongolia). ","Gora Altan-obo (Mongolia). ","Mongolia. Altan Ovoo Mountain. "],"west-coordinate":null,"east-coordinate":null,"north-coordinate":null,"south-coordinate":null,"marc-geo-code":null,"classification":null,"general-note":null}