{"type":"","identifier":"sh2009004335","alt-identifier":["sh2009004335"],"old-identifier":[""],"heading":["Arizona cottontop. "],"alt-heading":["Arizona cotton top. ","Arizona cottongrass. ","California cottontop. ","California crabgrass. ","Cotton-top (Digitaria californica). ","Cottongrass (Digitaria californica). ","Cottontop (Digitaria californica). ","Digitaria californica. ","Punta blanca (Plant). ","Trichachne californica. ","Crabgrass. "],"west-coordinate":null,"east-coordinate":null,"north-coordinate":null,"south-coordinate":null,"marc-geo-code":null,"classification":["QK495.G74. "],"general-note":null}