{"type":"","identifier":"sh2004001224","alt-identifier":["sh2004001224"],"old-identifier":[""],"heading":["Spea multiplicata. "],"alt-heading":["Desert spadefoot. ","Many-ribbed spea. ","Mexican spadefoot. ","Mexican spade-foot toad. ","New Mexican spea. ","New Mexico spadefoot. ","New Mexico spadefoot toad. ","Scaphiopus hammondii multiplicatus. ","Scaphiopus multiplicatus. ","Southern spadefoot. ","Spea. "],"west-coordinate":null,"east-coordinate":null,"north-coordinate":null,"south-coordinate":null,"marc-geo-code":null,"classification":["QL668.E33. Zoology. "],"general-note":null}