{"type":"","identifier":"sh2004003616","alt-identifier":["sh2004003616"],"old-identifier":[""],"heading":["Kok River (Burma and Thailand). "],"alt-heading":["Rivers. Burma. ","Rivers. Thailand. ","Khlong Kok (Burma and Thailand). ","Mae Kok River (Burma and Thailand). ","Mae Nam Kok (Burma and Thailand). ","Nam Hkok (Burma and Thailand). ","Kok River (Burma and Thailand). "],"west-coordinate":["E1000400"],"east-coordinate":["E1000400"],"north-coordinate":["N0080700"],"south-coordinate":["N0080700"],"marc-geo-code":null,"classification":null,"general-note":null}