{"type":"","identifier":"sh2005020336","alt-identifier":["sh2005020336"],"old-identifier":[""],"heading":["Trout cod. "],"alt-heading":["Blue nose (Fish). ","Bluenose. ","Cod, Trout. ","Gryptes brisbani. ","Gryptes brisbanii. ","Grystes brisbani. ","Grystes brisbanii. ","Grystes macquariensis. ","Maccullochella macquariensis. ","Oligorus gibbiceps. ","Oligorus mitchelii. ","Oligorus mitchellii. ","Maccullochella. "],"west-coordinate":null,"east-coordinate":null,"north-coordinate":null,"south-coordinate":null,"marc-geo-code":null,"classification":["QL638.P358. Zoology. "],"general-note":null}