{"type":"","identifier":"sh85009423","alt-identifier":["sh 85009423 "],"old-identifier":[""],"heading":["Attribution of news. "],"alt-heading":["Authority in the news, Citation of. ","Citation of authority in the news. ","News, Attribution of. ","News source identification. ","Sources, News. ","Confidential communications. Press. ","Journalistic ethics. ","Reporters and reporting. "],"west-coordinate":null,"east-coordinate":null,"north-coordinate":null,"south-coordinate":null,"marc-geo-code":null,"classification":null,"general-note":null}