{"type":"","identifier":"sh85024672","alt-identifier":["sh 85024672 "],"old-identifier":[""],"heading":["Chondrichthyes. "],"alt-heading":["Cartilaginous fishes. ","Chondrichthyan fishes. ","Chondrichthyans. ","Elasmobranch fishes. ","Elasmobranchi. ","Elasmobranchiate fishes. ","Elasmobranchii. ","Elasmobranchiomorphi. ","Elasmobranchs. ","Plagiostomi. ","Selachian fishes. ","Selachians. ","Selachii. ","Selachimorpha. ","Fishes. "],"west-coordinate":null,"east-coordinate":null,"north-coordinate":null,"south-coordinate":null,"marc-geo-code":null,"classification":["QL638.6. QL638.95. Zoology. "],"general-note":null}