{"type":"","identifier":"sh85082501","alt-identifier":["sh 85082501 "],"old-identifier":[""],"heading":["McAllister family. "],"alt-heading":["MacAlister family. ","McAlaster family. ","McAlester family. ","McAlister family. ","McAllaster family. ","McAllester family. ","McCalister family. ","McCallister family. ","McCollester family. ","McCollister family. "],"west-coordinate":null,"east-coordinate":null,"north-coordinate":null,"south-coordinate":null,"marc-geo-code":null,"classification":null,"general-note":null}