{"type":"","identifier":"sh85136865","alt-identifier":["sh 85136865 "],"old-identifier":[""],"heading":["Tranquilizing drugs. "],"alt-heading":["Antianxiety agents. ","Antianxiety drugs. ","Anxiolytic agents. ","Anxiolytic drugs. ","Anxiolytics. ","Ataractic drugs. ","Minor tranquilizers. ","Minor tranquilizing agents. ","Minor tranquilizing drugs. ","Tranquilizers. ","Psychotropic drugs. "],"west-coordinate":null,"east-coordinate":null,"north-coordinate":null,"south-coordinate":null,"marc-geo-code":null,"classification":["RM333. "],"general-note":null}