{"type":"","identifier":"sh85033754","alt-identifier":["sh 85033754 "],"old-identifier":[""],"heading":["Craniometry. "],"alt-heading":["Skull. Measurement. ","Cephalometry. ","Craniology. "],"west-coordinate":null,"east-coordinate":null,"north-coordinate":null,"south-coordinate":null,"marc-geo-code":null,"classification":["GN71. GN131. "],"general-note":["Here are entered works on methods of measuring the skull. Anthropological, archaeological, or ethnological works on skulls are entered under. Craniology.. Anatomical and pathological works on the skull are entered under. Skull.. "]}