{"type":"","identifier":"sh85112851","alt-identifier":["sh 85112851 "],"old-identifier":[""],"heading":["Rengma language. "],"alt-heading":["Injang language. ","Moiyui language. ","Mon language (Rengma). ","Mozhumi language. ","Nzong language. ","Nzonyu language. ","Rengama Naga language. ","Unza language. ","Naga languages. ","India. Languages. "],"west-coordinate":null,"east-coordinate":null,"north-coordinate":null,"south-coordinate":null,"marc-geo-code":null,"classification":["PL4001.R4. "],"general-note":null}