{"type":"","identifier":"sh85057446","alt-identifier":["sh 85057446 "],"old-identifier":[""],"heading":["Groton Heights, Battle of, Conn., 1781. "],"alt-heading":["Fort Griswold, Battle of, Conn., 1781. ","Groton Heights, Battle of, 1781. ","Connecticut. History. Revolution, 1775-1783. ","United States. History. Revolution, 1775-1783. Campaigns. "],"west-coordinate":null,"east-coordinate":null,"north-coordinate":null,"south-coordinate":null,"marc-geo-code":null,"classification":["E241.G8. "],"general-note":null}