{"type":"","identifier":"sh85057029","alt-identifier":["sh 85057029 "],"old-identifier":[""],"heading":["Grebo (African people). "],"alt-heading":["Glebo (African people). ","Grebo (African tribe). ","Gweabo (African people). ","Krebo (African people). ","Ethnology. Côte d'Ivoire. ","Ethnology. Liberia. ","Kru (African people). "],"west-coordinate":null,"east-coordinate":null,"north-coordinate":null,"south-coordinate":null,"marc-geo-code":null,"classification":["DT630.5.G6. "],"general-note":null}