{"type":"","identifier":"sh85073472","alt-identifier":["sh 85073472 "],"old-identifier":[""],"heading":["Kuril Islands (Russia). "],"alt-heading":["Islands. Russia (Federation). ","Chishima-retto (Russia). ","Kuril Islands (R.S.F.S.R.). ","Kurile Islands (Russia). ","Kurilʹskie ostrova (Russia). ","Russia (Federation). Kuril Islands. "],"west-coordinate":["E1520000"],"east-coordinate":["E1520000"],"north-coordinate":["N0461000"],"south-coordinate":["N0461000"],"marc-geo-code":null,"classification":null,"general-note":null}