{"type":"","identifier":"sh85094655","alt-identifier":["sh 85094655 "],"old-identifier":[""],"heading":["Olympic Mountains (Wash.). "],"alt-heading":["Mountains. Washington (State). ","Coast Range (Wash.). ","Olympian Mountains (Wash.). ","Olympic Range (Wash.). ","Olympus Range (Wash.). ","Coast Ranges. ","Washington (State). Olympic Mountains. "],"west-coordinate":["W1234005"],"east-coordinate":["W1234005"],"north-coordinate":["N0475219"],"south-coordinate":["N0475219"],"marc-geo-code":null,"classification":null,"general-note":null}