{"type":"","identifier":"sh85041544","alt-identifier":["sh 85041544 "],"old-identifier":[""],"heading":["Eleanor Roosevelt National Historic Site (N.Y.). "],"alt-heading":["Historic sites. New York (State). ","National parks and reserves. New York (State). ","Val-Kill (Hyde Park, N.Y.). ","New York (State). Eleanor Roosevelt National Historic Site. "],"west-coordinate":["W0735356"],"east-coordinate":["W0735356"],"north-coordinate":["N0414543"],"south-coordinate":["N0414543"],"marc-geo-code":null,"classification":null,"general-note":null}