{"type":"","identifier":"sh85071076","alt-identifier":["sh 85071076 "],"old-identifier":[""],"heading":["Jura Mountains (France and Switzerland). "],"alt-heading":["Mountains. France. ","Mountains. Switzerland. ","Jura (France and Switzerland). ","Monts du Jura (France and Switzerland). ","Monts Jura (France and Switzerland). ","Jura Mountains (France and Switzerland). "],"west-coordinate":null,"east-coordinate":null,"north-coordinate":null,"south-coordinate":null,"marc-geo-code":null,"classification":null,"general-note":null}