{"type":"","identifier":"sh85026344","alt-identifier":["sh 85026344 "],"old-identifier":[""],"heading":["Civil law. "],"alt-heading":["Law, Civil. ","Private law. ","Roman law. "],"west-coordinate":null,"east-coordinate":null,"north-coordinate":null,"south-coordinate":null,"marc-geo-code":null,"classification":null,"general-note":["Here are entered works on the laws regulating all the private relations of citizens to each other. Works on legal systems derived from Roman law are entered under. Civil law systems.. "]}