{"type":"","identifier":"sh85060038","alt-identifier":["sh 85060038 "],"old-identifier":[""],"heading":["Heliothis zea. "],"alt-heading":["Bollworm, New World. ","Bombyx obsoleta. ","Chloridea obsoleta. ","Corn earworm. ","Cotton bollworm. ","Earworm, Corn. ","Fruitworm, Tomato. ","Helicoverpa zea. ","Heliothis umbrosus. ","Tomato fruitworm. ","Heliothis. "],"west-coordinate":null,"east-coordinate":null,"north-coordinate":null,"south-coordinate":null,"marc-geo-code":null,"classification":["QL561.N7. Entomology. ","SB945.H28. Pest. "],"general-note":null}