{"type":"","identifier":"sh85022551","alt-identifier":["sh 85022551 "],"old-identifier":[""],"heading":["Gregorian chants. "],"alt-heading":["Catholic Church. Liturgy. ","Chant (Plain, Gregorian, etc.). ","Chants (Plain, Gregorian, etc.). ","Franco-Roman chants. ","Gregorian chant. ","Old Roman chants. ","Plainchant. ","Plainchants. ","Plainsong. ","Roman chants. ","Chants. ","Ambrosian chants. ","Beneventan chants. "],"west-coordinate":null,"east-coordinate":null,"north-coordinate":null,"south-coordinate":null,"marc-geo-code":null,"classification":null,"general-note":null}