{"type":"","identifier":"sh85073072","alt-identifier":["sh 85073072 "],"old-identifier":[""],"heading":["Korean Air Lines Incident, 1983. "],"alt-heading":["Downing of Korean Air Lines Flight 007, 1983. ","Flight 007 Incident, 1983. ","K.A.L. Flight 007 Incident, 1983. ","KAL Flight 007 Incident, 1983. ","Korean Air Lines Flight 007 Incident, 1983. ","Korean Airliner Incident, 1983. ","Shooting Down of Korean Air Lines Flight 007, 1983. ","South Korean Airliner Incident, 1983. ","Aircraft accidents. ","World politics. 1975-1985. "],"west-coordinate":null,"east-coordinate":null,"north-coordinate":null,"south-coordinate":null,"marc-geo-code":null,"classification":null,"general-note":null}