{"type":"","identifier":"sh85052971","alt-identifier":["sh 85052971 "],"old-identifier":[""],"heading":["Games of strategy (Mathematics). "],"alt-heading":["Games with rational pay-off (Mathematics). ","Rational games (Mathematics). ","Strategy, Games of (Mathematics). ","Game theory. ","Group theory. ","Mathematical optimization. ","Matrices. ","Topology. "],"west-coordinate":null,"east-coordinate":null,"north-coordinate":null,"south-coordinate":null,"marc-geo-code":null,"classification":["QA270. "],"general-note":null}