{"type":"","identifier":"sh85142461","alt-identifier":["sh 85142461 "],"old-identifier":[""],"heading":["Vecuronium bromide. "],"alt-heading":["Bisacetyloxypiperidinylandrostanylmethylpiperidinium bromide. ","Diacetoxypiperidinoandrostanylmethylpiperidinium bromide. ","Bromides. ","Neuromuscular blocking agents. ","Piperidine. "],"west-coordinate":null,"east-coordinate":null,"north-coordinate":null,"south-coordinate":null,"marc-geo-code":null,"classification":["RD86.V42. Anesthesia. "],"general-note":null}