{"type":"","identifier":"sh85063519","alt-identifier":["sh 85063519 "],"old-identifier":[""],"heading":["Hygiene. "],"alt-heading":["Body care. ","Cleanliness. ","Human body. Care and hygiene. ","Personal body care. ","Personal cleanliness. ","Personal hygiene. ","Medicine, Preventive. ","Health. ","Sanitation. "],"west-coordinate":null,"east-coordinate":null,"north-coordinate":null,"south-coordinate":null,"marc-geo-code":null,"classification":["RA770.5. Household hygiene. ","RA780. Personal hygiene. "],"general-note":["Here are entered works on personal body care and cleanliness. Works on optimal physical, mental, and social well-being, as well as how to achieve and preserve it, are entered under. Health.. "]}