{"type":"","identifier":"sh85148409","alt-identifier":["sh 85148409 "],"old-identifier":[""],"heading":["World War, 1939-1945. Equipment and supplies. "],"alt-heading":["World War, 1939-1945. Arms. ","World War, 1939-1945. Military supplies. ","World War, 1939-1945. Munitions. ","World War, 1939-1945. Ordnance. ","World War, 1939-1945. Supplies. ","World War, 1939-1945. War materials. ","World War, 1939-1945. Weapons. "],"west-coordinate":null,"east-coordinate":null,"north-coordinate":null,"south-coordinate":null,"marc-geo-code":null,"classification":null,"general-note":null}