{"type":"","identifier":"sh85080442","alt-identifier":["sh 85080442 "],"old-identifier":[""],"heading":["Mandingo (African people). "],"alt-heading":["Malinke (African people). ","Mandé (African people). ","Manding (African people). ","Mandingue (African people). ","Mandinka (African people). ","Mandino (African people). ","Maninka (African people). ","Maninkaalu (African people). ","Soce (African people). ","Sosse (African people). ","Ethnology. Africa, West. "],"west-coordinate":null,"east-coordinate":null,"north-coordinate":null,"south-coordinate":null,"marc-geo-code":null,"classification":["DT474.6.M36. West Africa. ","DT509.45.M34. Gambia. ","DT543.45.M34. Guinea. ","DT551.45.M36. Mali. "],"general-note":null}