{"type":"","identifier":"sh86003889","alt-identifier":["sh 86003889 "],"old-identifier":[""],"heading":["Clinical epidemiology. "],"alt-heading":["Epidemiology. "],"west-coordinate":null,"east-coordinate":null,"north-coordinate":null,"south-coordinate":null,"marc-geo-code":null,"classification":["RA652.2.C55. "],"general-note":["Here are entered works on the use of information about the occurrence and distribution of specific diseases and disorders in a community to aid in clinical diagnosis.. "]}