{"type":"","identifier":"sh86007520","alt-identifier":["sh 86007520 "],"old-identifier":[""],"heading":["Business parks. "],"alt-heading":["Enterprise parks. ","Office parks. ","Parks, Business. ","Industrial sites. "],"west-coordinate":null,"east-coordinate":null,"north-coordinate":null,"south-coordinate":null,"marc-geo-code":null,"classification":null,"general-note":["Here are entered works on sites with parklike surroundings containing office buildings or a mixture of light industrial, high technology, research and development, and general office buildings, often with parking lots, restaurants, and recreation areas.. "]}