{"type":"","identifier":"sh89004678","alt-identifier":["sh 89004678 "],"old-identifier":[""],"heading":["Home of Franklin D. Roosevelt National Historic Site (Hyde Park, N.Y.). "],"alt-heading":["Historic sites. New York (State). ","National parks and reserves. New York (State). ","Franklin D. Roosevelt National Historic Site (Hyde Park, N.Y.). "],"west-coordinate":["W0735617"],"east-coordinate":["W0735617"],"north-coordinate":["N0414601"],"south-coordinate":["N0414601"],"marc-geo-code":null,"classification":null,"general-note":null}