{"type":"","identifier":"sh89001097","alt-identifier":["sh 89001097 "],"old-identifier":[""],"heading":["Sister cities. "],"alt-heading":["Partner cities. ","Cities and towns. "],"west-coordinate":null,"east-coordinate":null,"north-coordinate":null,"south-coordinate":null,"marc-geo-code":null,"classification":null,"general-note":["Here are entered general works on the concept of sister cities. Works on individual sister cities are entered under the names of the individual cities with appropriate topical subdivision, with an additional entry under the heading. Sister cities.. "]}