{"type":"","identifier":"sh89005230","alt-identifier":["sh 89005230 "],"old-identifier":[""],"heading":["Yupik Eskimos. "],"alt-heading":["Kuskokwagmiut Eskimos. ","Kuskokwim Eskimos. ","Yulugpiaq Eskimos. ","Yupiak Eskimos. ","Yupiaq Eskimos. ","Yupiat Eskimos. ","Yu'ik Eskimos. ","Eskimos. Alaska. ","Eskimos. Russia (Federation). "],"west-coordinate":null,"east-coordinate":null,"north-coordinate":null,"south-coordinate":null,"marc-geo-code":null,"classification":["E99.E7. "],"general-note":null}