{"type":"","identifier":"sh91000792","alt-identifier":["sh 91000792 "],"old-identifier":[""],"heading":["Sankt Michael, Battle of, Sankt Michael in Obersteiermark, Austria, 1809. "],"alt-heading":["Sankt Michael in Obersteiermark (Austria), Battle of, 1809. ","St. Michael, Battle of, Sankt Michael in Obersteiermark, Austria, 1809. ","Napoleonic Wars, 1800-1815. Campaigns. Austria. "],"west-coordinate":null,"east-coordinate":null,"north-coordinate":null,"south-coordinate":null,"marc-geo-code":null,"classification":["DC234.63. "],"general-note":null}