{"type":"","identifier":"sh91005929","alt-identifier":["sh 91005929 "],"old-identifier":[""],"heading":["Beaver Dam Mountains Wilderness (Ariz. and Utah). "],"alt-heading":["National parks and reserves. Arizona. ","National parks and reserves. Utah. ","Wilderness areas. Arizona. ","Wilderness areas. Utah. ","Beaver Dam Mountains Wilderness (Ariz. and Utah). "],"west-coordinate":["W1134608"],"east-coordinate":["W1134608"],"north-coordinate":["N0365952"],"south-coordinate":["N0365952"],"marc-geo-code":null,"classification":null,"general-note":null}