{"type":"","identifier":"sh93003065","alt-identifier":["sh 93003065 "],"old-identifier":[""],"heading":["Limbum (African people). "],"alt-heading":["Bojin (African people). ","Limbom (African people). ","Llimbumi (African people). ","Ndzungle (African people). ","Ndzungli (African people). ","Njungene (African people). ","Nsungali (African people). ","Nsungli (African people). ","Nsungni (African people). ","Wimbum (African people). ","Wimbun (African people). ","Zungle (African people). ","Bantu-speaking peoples. ","Ethnology. Cameroon. "],"west-coordinate":null,"east-coordinate":null,"north-coordinate":null,"south-coordinate":null,"marc-geo-code":null,"classification":["DT571.L55. "],"general-note":null}