{"type":"","identifier":"sh94004420","alt-identifier":["sh 94004420 "],"old-identifier":[""],"heading":["Eames plywood folding tables. "],"alt-heading":["Card table, Eames. ","Dining table metal, Eames. ","DTM (Dining table metal). ","Folding legs table, Eames. ","Folding table, Eames. ","Incidental table, Eames. ","IT (Incidental table). ","Plywood folding tables, Eames. ","Eames furniture. ","Folding tables. "],"west-coordinate":null,"east-coordinate":null,"north-coordinate":null,"south-coordinate":null,"marc-geo-code":null,"classification":null,"general-note":null}