{"type":"","identifier":"sh95010674","alt-identifier":["sh 95010674 "],"old-identifier":[""],"heading":["ISO 14000 Series Standards. "],"alt-heading":["International Organization for Standardization 14000 Series Standards. ","ISO Standards Series 14000. ","Environmental protection. Standards. ","Industrial management. Environmental aspects. ","Production management. Environmental aspects. "],"west-coordinate":null,"east-coordinate":null,"north-coordinate":null,"south-coordinate":null,"marc-geo-code":null,"classification":null,"general-note":null}