{"type":"","identifier":"sh95006891","alt-identifier":["sh 95006891 "],"old-identifier":[""],"heading":["Pinta Island (Galapagos Islands). "],"alt-heading":["Islands. Ecuador. ","Abingdon Island (Galapagos Islands). ","Abington (Galapagos Islands). ","Abingtoni Island (Galapagos Islands). ","Isla Abingdon (Galapagos Islands). ","Isla Abingtoni (Galapagos Islands). ","Isla Pinta (Galapagos Islands). ","Galapagos Islands. ","Galapagos Islands. Pinta Island. "],"west-coordinate":["W0904400"],"east-coordinate":["W0904400"],"north-coordinate":["N0003500"],"south-coordinate":["N0003500"],"marc-geo-code":null,"classification":null,"general-note":null}