{"type":"","identifier":"sh95004105","alt-identifier":["sh 95004105 "],"old-identifier":[""],"heading":["Indian termination policy. "],"alt-heading":["Termination policy, Indian. ","Tribal termination policy. ","Indians of North America. Government relations. "],"west-coordinate":null,"east-coordinate":null,"north-coordinate":null,"south-coordinate":null,"marc-geo-code":null,"classification":null,"general-note":["Here are entered works on the cessation of the special relationship between the United States federal government and American Indian tribes that occurred during the 1950s and 1960s.. "]}