{"type":"","identifier":"sh95000657","alt-identifier":["sh 95000657 "],"old-identifier":[""],"heading":["Parque Nacional Los Haitises (Dominican Republic). "],"alt-heading":["National parks and reserves. Dominican Republic. ","Haitises, Parque Nacional Los (Dominican Republic). ","Los Haitises National Park (Dominican Republic). ","Dominican Republic. Parque Nacional Los Haitises. "],"west-coordinate":null,"east-coordinate":null,"north-coordinate":null,"south-coordinate":null,"marc-geo-code":null,"classification":null,"general-note":null}