{"type":"","identifier":"sh99014653","alt-identifier":["sh 99014653 "],"old-identifier":[""],"heading":["Balija (Indic people). "],"alt-heading":["Gazulu (Indic people). ","Junbi (Indic people). ","Kapu (Indic people). ","Kavarai (Indic people). ","Kavari (Indic people). ","Ontari (Indic people). ","Perike (Indic people). ","Telaga (Indic people). ","Vadugan (Indic people). ","Caste. India. ","Ethnology. India. "],"west-coordinate":null,"east-coordinate":null,"north-coordinate":null,"south-coordinate":null,"marc-geo-code":null,"classification":["DS432.B324. "],"general-note":null}